Metadata-Version: 2.1
Name: techyshiv-evenodd
Version: 1.0.1
Summary: A Python package to Check Even and Odd for any given numbers or list and return True , False & list based on data type provided
Home-page: https://github.com/techyshiv/Python-Package
Author: Shivang Saxena
Author-email: shivangsaxena177@gmail.com
License: MIT
Classifier: License :: OSI Approved :: MIT License
Classifier: Programming Language :: Python :: 3
Classifier: Programming Language :: Python :: 3.7
License-File: LICENSE
